single_cycle_risc-v_processor/proc.v
module top(
  input clk, rst,
  output [31:0] Alu_result,
  output [31:0] Immediate_result,
  output [31:0] PC,
  output [31:0] Instruction,
  output [4:0] rs1,
  output [4:0] rs2,
  output [31:0] Data1,
  output [31:0] Data2
);

  wire [31:0] pc_i, pc_o;
  wire [31:0] ins_out;

  wire [6:0] opcode, Funct7;
  wire [4:0] Rs1, Rs2, Rd;
  wire [2:0] Funct3;
  wire [11:0] imm;

  wire [1:0] aluSel; // control signal wires
  wire regWrite, bSel, MEMRW; 

  wire [31:0] imm_out; // imm from immediate generator
  wire [31:0] alu_out, dataMem_out; 
  wire [31:0] dataW;
  wire [31:0] data1, data2;

  wire [31:0] mux_out; // data2 or imm_out
  wire [31:0] alu_resultt;

  program_coutner p0(clk, rst, pc_i, pc_o);
  adder a0(pc_o, 32'd4, pc_i);
  instruction_memory i0(pc_o, rst, ins_out); // got the instruction

  decoder d0(ins_out, opcode, Rd, Funct3, Rs1, Rs2, Funct7, imm);
  control_unit c0(ins_out, regWrite, bSel, WBSel, MEMRW, aluSel);

  regfile r0(clk, regWrite, Rs1, Rs2, Rd, dataW, data1, data2);
  
  imm_gen im0(ins_out, imm_out);
  mux m0(imm_out, data2, bSel, mux_out);

  alu al0(aluSel, data1, mux_out, alu_out);
  data_memory dm0(alu_out, MEMRW, dataMem_out);  
  
  mux m1(dataMem_out, alu_out, WBSel, dataW);

  assign Alu_result = dataW;
  assign Immediate_result = imm_out;
  assign PC = pc_i;
  assign Instruction = ins_out;
  assign rs1 = Rs1;
  assign rs2 = Rs2;
  assign Data1 = data1;
  assign Data2 = data2;

endmodule


module control_unit (
  input [31:0] instruction,
  output reg RegWrite, BSel, WBSel, MEMRW, 
  output reg [1:0] ALUSel
);
  
  wire [6:0] opcode = instruction [6:0];
  wire [2:0] funct3 = instruction [14:12];
  wire [6:0] funct7 = instruction [31:25];

  always @(*) begin
    casez ({opcode, funct3, funct7})
      17'b0110011_000_0000000: begin  // add
        RegWrite = 1;
        BSel = 0;
        ALUSel = 2'b00;
        WBSel = 1;
        MEMRW = 1'bx;
      end
      17'b0010011_000_???????: begin  // addi
        RegWrite = 1;
        BSel = 1;
        ALUSel = 2'b00;
        WBSel = 1;
        MEMRW = 1'bx;
      end
      17'b0000011_010_???????: begin  // addi
        RegWrite = 1;
        BSel = 1;
        ALUSel = 2'b00;
        WBSel = 0;
        MEMRW = 0;
      end
      default: begin
        RegWrite = 0;
        BSel = 0;
        ALUSel = 2'b00;
      end
  endcase

  end

endmodule

module program_coutner (
  input clk, rst,   
  input [31:0] pc_in,
  output reg [31:0] pc_out 
);

  always @(posedge clk) begin
    if(rst) begin
      pc_out <= 32'b0;
    end else begin
      pc_out <= pc_in;
    end
  end

endmodule

module adder(
  input [31:0] a, b,
  output [31:0] sum
);
  
  assign sum = a + b;

endmodule

module instruction_memory (
  input [31:0] address,
  input rst,
  output [31:0] instruction
);
  
  reg [7:0] inst_mem [1023:0];
  
  assign instruction = {inst_mem[address+3], inst_mem[address+2], inst_mem[address+1], inst_mem[address]};
  
  always @(rst) begin
    if(rst == 1) begin
    
    // add x3 x2 x1
    inst_mem[3] = 8'h00;
    inst_mem[2] = 8'h11;
    inst_mem[1] = 8'h01;
    inst_mem[0] = 8'hb3;
    
    // addi x4 x2 25
    inst_mem[7] = 8'h83;
    inst_mem[6] = 8'h40;
    inst_mem[5] = 8'h82;
    inst_mem[4] = 8'h13;

    // lw x10 1000(x2)
    inst_mem[27] = 8'h3e;
    inst_mem[26] = 8'h81;
    inst_mem[25] = 8'h25;
    inst_mem[24] = 8'h03;

    end

  end


endmodule

module imm_gen (
  input [31:0] instruction,
  output reg [31:0] immediate
);
  
  parameter i_opcode1 = 7'b0010011;

  wire [6:0] opcode = instruction [6:0];

  wire [11:0] immediate_i = instruction[31:20];

  always @(*) begin
    case(opcode) 
      i_opcode1: immediate = {{20{instruction[31]}}, immediate_i};
      default: immediate = 32'bx;
    endcase
  end
  
endmodule

module decoder (
  input [31:0] instruction,
  output  [6:0] OPCODE,
  output reg [4:0] rd,
  output reg [2:0] funct3,
  output reg [4:0] rs1, rs2,
  output reg [6:0] funct7,
  output reg [11:0] immediate
);
  
  wire [6:0] opcode = instruction [6:0]; 

  parameter arithmetic_r = 7'b0110011;
  parameter arithmetic_i = 7'b0010011;

  always @(*) begin
    case(opcode)

      arithmetic_r: begin
        rd = instruction[12:7];
        funct3 = instruction[14:12];
        rs1 = instruction[19:15];
        rs2 = instruction[24:20];
        funct7 = instruction[31:25];
        immediate = 12'bx;
      end

      arithmetic_i: begin
        rd = instruction[11:7];
        funct3 = instruction[14:12];
        rs1 = instruction[19:15];
        immediate = instruction[31:20];
        rs2 = 5'bx;
        funct7 = 7'bx;
      end
      
      default: begin
        rd = 5'b0; 
        funct3 = 3'b0;
        rs1 = 5'b0;
        rs2 = 5'b0;
        funct7 = 7'b0;
        immediate = 12'b0;
      end
    
    endcase
  end

  assign OPCODE = instruction [6:0]; 


endmodule

module regfile (
  input clk, RegWrite,
  input [4:0] rs1, rs2, rd,
  input [31:0] WriteData,
  output [31:0] ReadData1, ReadData2
);
  reg [31:0] Reg [31:0];
  
  initial begin
    Reg[1]=5;
    Reg[2]=6;
    Reg[3]=7;
    Reg[4]=2;	
    Reg[5]=3;
    Reg[6]=1;	
    Reg[7]=0;
    Reg[8]=9;
    Reg[9]=23;
    Reg[10]=11;
  
    Reg[11]=5;
    Reg[12]=6;
    Reg[13]=7;
    Reg[14]=2;	
    Reg[15]=3;
    Reg[16]=1;	
    Reg[17]=0;
    Reg[18]=32;
    Reg[19]=15;
    Reg[20]=11;
    
    Reg[21]=5;
    Reg[22]=6;
    Reg[23]=7;
    Reg[24]=2;	
    Reg[25]=3;
    Reg[26]=1;	
    Reg[27]=0;
    Reg[28]=28;
    Reg[29]=6;
    Reg[30]=17;
    Reg[31]=31;
  end

  always @(posedge clk) begin
    Reg[0] = 0;
    
    if(RegWrite) begin
      Reg[rd] = WriteData;
    end

  end

  assign ReadData1 = Reg[rs1]; 
  assign ReadData2 = Reg[rs2];

endmodule

module mux (
  input [31:0] a, b, 
  input s,
  output [31:0] y
);

  assign y = s ? a : b;

endmodule

module alu (
  input [1:0] ALUSel,
  input [31:0] data1, data2,
  output reg [31:0] result
);

  always @(*) begin
    case(ALUSel) 
      2'b00: result = data1 + data2;
      2'b10: result = data1 || data2;
      default: result = 32'b0; 
    endcase
  end

endmodule

module data_memory(
  input [31:0] addr,
  input MEMRW, 
  output reg [31:0] dataR
);
  
  reg [7:0] data_mem [1023:0];

  always @(*) begin
    if(MEMRW)
    begin
      dataR[7:0] = data_mem[addr];    
      dataR[15:8] = data_mem[addr];    
      dataR[23:16] = data_mem[addr];    
      dataR[31:24] = data_mem[addr];    
    end 
  end 

endmodule

single_cycle_risc-v_processor/proc_tb.v
`timescale 1ns / 1ps


module proc_tb();

  reg clk, rst;
  wire [31:0] Alu_result;
  wire [31:0] Immediate_result;
  wire [31:0] PC;
  wire [31:0] Instruction;
  wire [4:0] rs1;
  wire [4:0] rs2;
  wire [31:0] Data1;
  wire [31:0] Data2;
  

  top dut(
    .clk(clk),
    .rst(rst),
    .Alu_result(Alu_result),
    .Immediate_result(Immediate_result),
    .PC(PC),
    .Instruction(Instruction),
    .rs1(rs1),
    .rs2(rs2),
    .Data1(Data1),
    .Data2(Data2)
  );

  initial begin
    forever #30 clk = ~clk;
  end

  initial begin
    clk = 1;

    $dumpfile("proc_tb.vcd");
    $dumpvars(0, proc_tb);

    
    rst = 1;

    #20 rst = 0;
    
    #1000 $finish;


  end

endmodule

single_cycle_risc-v_processor/proc_tb.vcd
$date
	Sat Feb 15 02:39:11 2025
$end
$version
	Icarus Verilog
$end
$timescale
	1ps
$end
$scope module proc_tb $end
$var wire 5 ! rs2 [4:0] $end
$var wire 5 " rs1 [4:0] $end
$var wire 32 # PC [31:0] $end
$var wire 32 $ Instruction [31:0] $end
$var wire 32 % Immediate_result [31:0] $end
$var wire 32 & Data2 [31:0] $end
$var wire 32 ' Data1 [31:0] $end
$var wire 32 ( Alu_result [31:0] $end
$var reg 1 ) clk $end
$var reg 1 * rst $end
$scope module dut $end
$var wire 32 + Alu_result [31:0] $end
$var wire 32 , Data1 [31:0] $end
$var wire 32 - Data2 [31:0] $end
$var wire 32 . Immediate_result [31:0] $end
$var wire 32 / Instruction [31:0] $end
$var wire 32 0 PC [31:0] $end
$var wire 1 ) clk $end
$var wire 5 1 rs1 [4:0] $end
$var wire 5 2 rs2 [4:0] $end
$var wire 1 * rst $end
$var wire 1 3 regWrite $end
$var wire 32 4 pc_o [31:0] $end
$var wire 32 5 pc_i [31:0] $end
$var wire 7 6 opcode [6:0] $end
$var wire 32 7 mux_out [31:0] $end
$var wire 32 8 ins_out [31:0] $end
$var wire 32 9 imm_out [31:0] $end
$var wire 12 : imm [11:0] $end
$var wire 32 ; dataW [31:0] $end
$var wire 32 < dataMem_out [31:0] $end
$var wire 32 = data2 [31:0] $end
$var wire 32 > data1 [31:0] $end
$var wire 1 ? bSel $end
$var wire 32 @ alu_out [31:0] $end
$var wire 2 A aluSel [1:0] $end
$var wire 1 B WBSel $end
$var wire 5 C Rs2 [4:0] $end
$var wire 5 D Rs1 [4:0] $end
$var wire 5 E Rd [4:0] $end
$var wire 1 F MEMRW $end
$var wire 7 G Funct7 [6:0] $end
$var wire 3 H Funct3 [2:0] $end
$scope module a0 $end
$var wire 32 I b [31:0] $end
$var wire 32 J sum [31:0] $end
$var wire 32 K a [31:0] $end
$upscope $end
$scope module al0 $end
$var wire 32 L data2 [31:0] $end
$var wire 32 M data1 [31:0] $end
$var wire 2 N ALUSel [1:0] $end
$var reg 32 O result [31:0] $end
$upscope $end
$scope module c0 $end
$var wire 7 P opcode [6:0] $end
$var wire 32 Q instruction [31:0] $end
$var wire 7 R funct7 [6:0] $end
$var wire 3 S funct3 [2:0] $end
$var reg 2 T ALUSel [1:0] $end
$var reg 1 ? BSel $end
$var reg 1 F MEMRW $end
$var reg 1 3 RegWrite $end
$var reg 1 B WBSel $end
$upscope $end
$scope module d0 $end
$var wire 7 U opcode [6:0] $end
$var wire 32 V instruction [31:0] $end
$var wire 7 W OPCODE [6:0] $end
$var parameter 7 X arithmetic_i $end
$var parameter 7 Y arithmetic_r $end
$var reg 3 Z funct3 [2:0] $end
$var reg 7 [ funct7 [6:0] $end
$var reg 12 \ immediate [11:0] $end
$var reg 5 ] rd [4:0] $end
$var reg 5 ^ rs1 [4:0] $end
$var reg 5 _ rs2 [4:0] $end
$upscope $end
$scope module dm0 $end
$var wire 1 F MEMRW $end
$var wire 32 ` addr [31:0] $end
$var reg 32 a dataR [31:0] $end
$upscope $end
$scope module i0 $end
$var wire 1 * rst $end
$var wire 32 b instruction [31:0] $end
$var wire 32 c address [31:0] $end
$upscope $end
$scope module im0 $end
$var wire 32 d instruction [31:0] $end
$var wire 7 e opcode [6:0] $end
$var wire 12 f immediate_i [11:0] $end
$var parameter 7 g i_opcode1 $end
$var reg 32 h immediate [31:0] $end
$upscope $end
$scope module m0 $end
$var wire 32 i a [31:0] $end
$var wire 1 ? s $end
$var wire 32 j y [31:0] $end
$var wire 32 k b [31:0] $end
$upscope $end
$scope module m1 $end
$var wire 32 l a [31:0] $end
$var wire 32 m b [31:0] $end
$var wire 1 B s $end
$var wire 32 n y [31:0] $end
$upscope $end
$scope module p0 $end
$var wire 1 ) clk $end
$var wire 32 o pc_in [31:0] $end
$var wire 1 * rst $end
$var reg 32 p pc_out [31:0] $end
$upscope $end
$scope module r0 $end
$var wire 32 q ReadData1 [31:0] $end
$var wire 32 r ReadData2 [31:0] $end
$var wire 1 3 RegWrite $end
$var wire 32 s WriteData [31:0] $end
$var wire 1 ) clk $end
$var wire 5 t rd [4:0] $end
$var wire 5 u rs1 [4:0] $end
$var wire 5 v rs2 [4:0] $end
$upscope $end
$upscope $end
$upscope $end
$enddefinitions $end
$comment Show the parameter values. $end
$dumpall
b10011 g
b110011 Y
b10011 X
$end
#0
$dumpvars
b1 v
b10 u
b11 t
bx s
b101 r
b110 q
b0 p
b100 o
bx n
b1011 m
bx l
b101 k
b101 j
bx i
bx h
b1 f
b110011 e
b100010000000110110011 d
b0 c
b100010000000110110011 b
bx a
b1011 `
b1 _
b10 ^
b11 ]
bx \
b0 [
b0 Z
b110011 W
b100010000000110110011 V
b110011 U
b0 T
b0 S
b0 R
b100010000000110110011 Q
b110011 P
b1011 O
b0 N
b110 M
b101 L
b0 K
b100 J
b100 I
b0 H
b0 G
xF
b11 E
b10 D
b1 C
1B
b0 A
b1011 @
0?
b110 >
b101 =
bx <
bx ;
bx :
bx 9
b100010000000110110011 8
b101 7
b110011 6
b100 5
b0 4
13
b1 2
b10 1
b100 0
b100010000000110110011 /
bx .
b101 -
b110 ,
bx +
1*
1)
bx (
b110 '
b101 &
bx %
b100010000000110110011 $
b100 #
b10 "
b1 !
$end
#20000
0*
#30000
0)
#60000
b100000110100 :
b100000110100 \
b11111111111111111111100000110100 %
b11111111111111111111100000110100 .
b11111111111111111111100000110100 9
b11111111111111111111100000110100 h
b11111111111111111111100000110100 i
1?
b11111111111111111111100000110100 7
b11111111111111111111100000110100 L
b11111111111111111111100000110100 j
b11111111111111111111100000111001 @
b11111111111111111111100000111001 O
b11111111111111111111100000111001 `
b11111111111111111111100000111001 m
b10011 e
b10011 6
b10011 W
b10011 U
b10011 P
b100000110100 f
b1000001 R
bx G
bx [
bx &
bx -
bx =
bx k
bx r
bx !
bx 2
bx C
bx _
bx v
b101 '
b101 ,
b101 >
b101 M
b101 q
b1 "
b1 1
b1 D
b1 ^
b1 u
b100 E
b100 ]
b100 t
b10000011010000001000001000010011 $
b10000011010000001000001000010011 /
b10000011010000001000001000010011 8
b10000011010000001000001000010011 Q
b10000011010000001000001000010011 V
b10000011010000001000001000010011 b
b10000011010000001000001000010011 d
b1000 #
b1000 0
b1000 5
b1000 J
b1000 o
b100 4
b100 K
b100 c
b100 p
1)
#90000
0)
#120000
b0 G
b0 [
b0 &
b0 -
b0 =
b0 k
b0 r
b0 !
b0 2
b0 C
b0 _
b0 v
0?
03
b0 @
b0 O
b0 `
b0 m
b0 7
b0 L
b0 j
bx e
bx 6
bx W
bx U
bx P
bx S
bx f
bx R
b0 :
b0 \
b0 '
b0 ,
b0 >
b0 M
b0 q
b0 "
b0 1
b0 D
b0 ^
b0 u
b0 H
b0 Z
b0 E
b0 ]
b0 t
bx %
bx .
bx 9
bx h
bx i
bx $
bx /
bx 8
bx Q
bx V
bx b
bx d
b1100 #
b1100 0
b1100 5
b1100 J
b1100 o
b1000 4
b1000 K
b1000 c
b1000 p
1)
#150000
0)
#180000
b10000 #
b10000 0
b10000 5
b10000 J
b10000 o
b1100 4
b1100 K
b1100 c
b1100 p
1)
#210000
0)
#240000
b10100 #
b10100 0
b10100 5
b10100 J
b10100 o
b10000 4
b10000 K
b10000 c
b10000 p
1)
#270000
0)
#300000
b11000 #
b11000 0
b11000 5
b11000 J
b11000 o
b10100 4
b10100 K
b10100 c
b10100 p
1)
#330000
0)
#360000
bx @
bx O
bx `
bx m
bx (
bx +
bx ;
bx n
bx s
bx 7
bx L
bx j
0F
0B
1?
13
b11 e
b11 6
b11 W
b11 U
b11 P
b10 S
b1111101000 f
b11111 R
b111110100000010010010100000011 $
b111110100000010010010100000011 /
b111110100000010010010100000011 8
b111110100000010010010100000011 Q
b111110100000010010010100000011 V
b111110100000010010010100000011 b
b111110100000010010010100000011 d
b11100 #
b11100 0
b11100 5
b11100 J
b11100 o
b11000 4
b11000 K
b11000 c
b11000 p
1)
#390000
0)
#420000
0?
03
bx e
bx 6
bx W
bx U
bx P
bx S
bx f
bx R
bx $
bx /
bx 8
bx Q
bx V
bx b
bx d
b100000 #
b100000 0
b100000 5
b100000 J
b100000 o
b11100 4
b11100 K
b11100 c
b11100 p
bx '
bx ,
bx >
bx M
bx q
bx &
bx -
bx =
bx k
bx r
1)
#450000
0)
#480000
b100100 #
b100100 0
b100100 5
b100100 J
b100100 o
b100000 4
b100000 K
b100000 c
b100000 p
b0 (
b0 +
b0 ;
b0 n
b0 s
b0 @
b0 O
b0 `
b0 m
b0 7
b0 L
b0 j
b0 '
b0 ,
b0 >
b0 M
b0 q
b0 &
b0 -
b0 =
b0 k
b0 r
1)
#510000
0)
#540000
b101000 #
b101000 0
b101000 5
b101000 J
b101000 o
b100100 4
b100100 K
b100100 c
b100100 p
1)
#570000
0)
#600000
b101100 #
b101100 0
b101100 5
b101100 J
b101100 o
b101000 4
b101000 K
b101000 c
b101000 p
1)
#630000
0)
#660000
b110000 #
b110000 0
b110000 5
b110000 J
b110000 o
b101100 4
b101100 K
b101100 c
b101100 p
1)
#690000
0)
#720000
b110100 #
b110100 0
b110100 5
b110100 J
b110100 o
b110000 4
b110000 K
b110000 c
b110000 p
1)
#750000
0)
#780000
b111000 #
b111000 0
b111000 5
b111000 J
b111000 o
b110100 4
b110100 K
b110100 c
b110100 p
1)
#810000
0)
#840000
b111100 #
b111100 0
b111100 5
b111100 J
b111100 o
b111000 4
b111000 K
b111000 c
b111000 p
1)
#870000
0)
#900000
b1000000 #
b1000000 0
b1000000 5
b1000000 J
b1000000 o
b111100 4
b111100 K
b111100 c
b111100 p
1)
#930000
0)
#960000
b1000100 #
b1000100 0
b1000100 5
b1000100 J
b1000100 o
b1000000 4
b1000000 K
b1000000 c
b1000000 p
1)
#990000
0)
#1020000
b1001000 #
b1001000 0
b1001000 5
b1001000 J
b1001000 o
b1000100 4
b1000100 K
b1000100 c
b1000100 p
1)
