single_cycle_risc-v_processor/proc.v
module top(
  input clk, rst,
  output [31:0] Alu_result,
  output [31:0] Immediate_result,
  output [31:0] PC,
  output [31:0] Instruction,
  output [4:0] rs1,
  output [4:0] rs2,
  output [31:0] Data1,
  output [31:0] Data2,
  output [31:0] DataW,
  output [31:0] DataMem_Out 
);

  wire [31:0] pc_i, pc_o;
  wire [31:0] ins_out;

  wire [6:0] opcode, Funct7;
  wire [4:0] Rs1, Rs2, Rd;
  wire [2:0] Funct3;
  wire [11:0] imm;

  wire [1:0] aluSel; // control signal wires
  wire regWrite, bSel, MEMRW; 

  wire [31:0] imm_out; // imm from immediate generator
  wire [31:0] alu_out, dataMem_out; 
  wire [31:0] dataW;
  wire [31:0] data1, data2;

  wire [31:0] mux_out; // data2 or imm_out
  wire [31:0] alu_resultt;

  program_coutner p0(clk, rst, pc_i, pc_o);
  adder a0(pc_o, 32'd4, pc_i);
  instruction_memory i0(pc_o, rst, ins_out); // got the instruction

  decoder d0(ins_out, opcode, Rd, Funct3, Rs1, Rs2, Funct7, imm);
  control_unit c0(ins_out, regWrite, bSel, WBSel, MEMRW, aluSel);

  regfile r0(clk, regWrite, Rs1, Rs2, Rd, dataW, data1, data2);
  
  imm_gen im0(ins_out, imm_out);
  mux m0(imm_out, data2, bSel, mux_out);

  alu al0(aluSel, data1, mux_out, alu_out);
  data_memory dm0(alu_out, MEMRW, dataMem_out);  
  
  mux m1(alu_out, dataMem_out, WBSel, dataW);

  assign DataW = dataW;
  assign DataMem_Out = dataMem_out;
  assign Alu_result = alu_out;
  assign Immediate_result = imm_out;
  assign PC = pc_i;
  assign Instruction = ins_out;
  assign rs1 = Rs1;
  assign rs2 = Rs2;
  assign Data1 = data1;
  assign Data2 = data2;

endmodule


module control_unit (
  input [31:0] instruction,
  output reg RegWrite, BSel, WBSel, MEMRW, 
  output reg [1:0] ALUSel
);
  
  wire [6:0] opcode = instruction [6:0];
  wire [2:0] funct3 = instruction [14:12];
  wire [6:0] funct7 = instruction [31:25];

  always @(*) begin
    casez ({opcode, funct3, funct7})
      17'b0110011_000_0000000: begin  // add
        RegWrite = 1;
        BSel = 0;
        ALUSel = 2'b00;
        WBSel = 1;
        MEMRW = 1'bx;
      end
      17'b0010011_000_???????: begin  // addi
        RegWrite = 1;
        BSel = 1;
        ALUSel = 2'b00;
        WBSel = 1;
        MEMRW = 1'bx;
      end
      17'b0000011_010_???????: begin  // addi
        RegWrite = 1;
        BSel = 1;
        ALUSel = 2'b00;
        WBSel = 0;
        MEMRW = 0;
      end
      default: begin
        RegWrite = 0;
        BSel = 0;
        ALUSel = 2'b00;
      end
  endcase

  end

endmodule

module program_coutner (
  input clk, rst,   
  input [31:0] pc_in,
  output reg [31:0] pc_out 
);

  always @(posedge clk) begin
    if(rst) begin
      pc_out <= 32'b0;
    end else begin
      pc_out <= pc_in;
    end
  end

endmodule

module adder(
  input [31:0] a, b,
  output [31:0] sum
);
  
  assign sum = a + b;

endmodule

module instruction_memory (
  input [31:0] address,
  input rst,
  output [31:0] instruction
);
  
  reg [7:0] inst_mem [1023:0];
  
  assign instruction = {inst_mem[address+3], inst_mem[address+2], inst_mem[address+1], inst_mem[address]};
  
  always @(rst) begin
    if(rst == 1) begin
    
    // add x3 x2 x1
    inst_mem[3] = 8'h00;
    inst_mem[2] = 8'h11;
    inst_mem[1] = 8'h01;
    inst_mem[0] = 8'hb3;
    
    // addi x4 x2 25
    inst_mem[7] = 8'h83;
    inst_mem[6] = 8'h40;
    inst_mem[5] = 8'h82;
    inst_mem[4] = 8'h13;

    // lw x10 1000(x2)
    inst_mem[11] = 8'h3e;
    inst_mem[10] = 8'h81;
    inst_mem[9] = 8'h25;
    inst_mem[8] = 8'h03;

    end

  end


endmodule

module imm_gen (
  input [31:0] instruction,
  output reg [31:0] immediate
);
  
  parameter i_opcode1 = 7'b0010011;
  parameter i_opcode2 = 7'b0000011;

  wire [6:0] opcode = instruction [6:0];

  wire [11:0] immediate_i = instruction[31:20];

  always @(*) begin
    case(opcode) 
      i_opcode1, i_opcode2: immediate = {{20{instruction[31]}}, immediate_i};
      default: immediate = 32'bx;
    endcase
  end
  
endmodule

module decoder (
  input [31:0] instruction,
  output  [6:0] OPCODE,
  output reg [4:0] rd,
  output reg [2:0] funct3,
  output reg [4:0] rs1, rs2,
  output reg [6:0] funct7,
  output reg [11:0] immediate
);
  
  wire [6:0] opcode = instruction; 

  parameter arithmetic_r = 7'b0110011;
  parameter arithmetic_i1 = 7'b0010011;
  parameter arithmetic_i2 = 7'b0000011;

  always @(*) begin
    case(opcode)

      arithmetic_r: begin
        rd = instruction[12:7];
        funct3 = instruction[14:12];
        rs1 = instruction[19:15];
        rs2 = instruction[24:20];
        funct7 = instruction[31:25];
        immediate = 12'bx;
      end

      arithmetic_i1, arithmetic_i2: begin
        rd = instruction[11:7];
        funct3 = instruction[14:12];
        rs1 = instruction[19:15];
        immediate = instruction[31:20];
        rs2 = 5'bx;
        funct7 = 7'bx;
      end
      
      default: begin
        rd = 5'b0; 
        funct3 = 3'b0;
        rs1 = 5'b0;
        rs2 = 5'b0;
        funct7 = 7'b0;
        immediate = 12'b0;
      end
    
    endcase
  end

  assign OPCODE = instruction [6:0]; 


endmodule

module regfile (
  input clk, RegWrite,
  input [4:0] rs1, rs2, rd,
  input [31:0] WriteData,
  output [31:0] ReadData1, ReadData2
);
  reg [31:0] Reg [31:0];
  
  initial begin
    Reg[1]=5;
    Reg[2]=6;
    Reg[3]=7;
    Reg[4]=2;	
    Reg[5]=3;
    Reg[6]=1;	
    Reg[7]=0;
    Reg[8]=9;
    Reg[9]=23;
    Reg[10]=11;
  
    Reg[11]=5;
    Reg[12]=6;
    Reg[13]=7;
    Reg[14]=2;	
    Reg[15]=3;
    Reg[16]=1;	
    Reg[17]=0;
    Reg[18]=32;
    Reg[19]=15;
    Reg[20]=11;
    
    Reg[21]=5;
    Reg[22]=6;
    Reg[23]=7;
    Reg[24]=2;	
    Reg[25]=3;
    Reg[26]=1;	
    Reg[27]=0;
    Reg[28]=28;
    Reg[29]=6;
    Reg[30]=17;
    Reg[31]=31;
  end

  always @(posedge clk) begin
    Reg[0] = 0;
    
    if(RegWrite) begin
      Reg[rd] = WriteData;
    end

  end

  assign ReadData1 = Reg[rs1]; 
  assign ReadData2 = Reg[rs2];

endmodule

module mux (
  input [31:0] a, b, 
  input s,
  output [31:0] y
);

  assign y = s ? a : b;

endmodule

module alu (
  input [1:0] ALUSel,
  input [31:0] data1, data2,
  output reg [31:0] result
);

  always @(*) begin
    case(ALUSel) 
      2'b00: result = data1 + data2;
      2'b10: result = data1 || data2;
      default: result = 32'b0; 
    endcase
  end

endmodule

module data_memory(
  input [31:0] addr,
  input MEMRW, 
  output reg [31:0] dataR
);
  
  reg [7:0] data_mem [1023:0];

  always @(*) begin
    if(MEMRW)
    begin
      dataR[7:0] = data_mem[addr];    
      dataR[15:8] = data_mem[addr];    
      dataR[23:16] = data_mem[addr];    
      dataR[31:24] = data_mem[addr];    
    end 
  end 

endmodule

single_cycle_risc-v_processor/proc_tb.v
`timescale 1ns / 1ps


module proc_tb();

  reg clk, rst;
  wire [31:0] Alu_result;
  wire [31:0] Immediate_result;
  wire [31:0] PC;
  wire [31:0] Instruction;
  wire [4:0] rs1;
  wire [4:0] rs2;
  wire [31:0] Data1;
  wire [31:0] Data2;
  wire [31:0] DataW; 
  wire [31:0] DataMem_Out;

  top dut(
    .clk(clk),
    .rst(rst),
    .Alu_result(Alu_result),
    .Immediate_result(Immediate_result),
    .PC(PC),
    .Instruction(Instruction),
    .rs1(rs1),
    .rs2(rs2),
    .Data1(Data1),
    .Data2(Data2),
    .DataW(DataW),
    .DataMem_Out(DataMem_Out)
  );

  initial begin
    forever #20 clk = ~clk;
  end

  initial begin
    clk = 1;

    $dumpfile("proc_tb.vcd");
    $dumpvars(0, proc_tb);

    
    rst = 1;

    #20 rst = 0;
    
    #1000 $finish;


  end

endmodule

single_cycle_risc-v_processor/proc_tb.vcd
$date
	Sat Feb 15 16:11:05 2025
$end
$version
	Icarus Verilog
$end
$timescale
	1ps
$end
$scope module proc_tb $end
$var wire 5 ! rs2 [4:0] $end
$var wire 5 " rs1 [4:0] $end
$var wire 32 # PC [31:0] $end
$var wire 32 $ Instruction [31:0] $end
$var wire 32 % Immediate_result [31:0] $end
$var wire 32 & DataW [31:0] $end
$var wire 32 ' DataMem_Out [31:0] $end
$var wire 32 ( Data2 [31:0] $end
$var wire 32 ) Data1 [31:0] $end
$var wire 32 * Alu_result [31:0] $end
$var reg 1 + clk $end
$var reg 1 , rst $end
$scope module dut $end
$var wire 32 - Alu_result [31:0] $end
$var wire 32 . Data1 [31:0] $end
$var wire 32 / Data2 [31:0] $end
$var wire 32 0 DataMem_Out [31:0] $end
$var wire 32 1 DataW [31:0] $end
$var wire 32 2 Immediate_result [31:0] $end
$var wire 32 3 Instruction [31:0] $end
$var wire 32 4 PC [31:0] $end
$var wire 1 + clk $end
$var wire 5 5 rs1 [4:0] $end
$var wire 5 6 rs2 [4:0] $end
$var wire 1 , rst $end
$var wire 1 7 regWrite $end
$var wire 32 8 pc_o [31:0] $end
$var wire 32 9 pc_i [31:0] $end
$var wire 7 : opcode [6:0] $end
$var wire 32 ; mux_out [31:0] $end
$var wire 32 < ins_out [31:0] $end
$var wire 32 = imm_out [31:0] $end
$var wire 12 > imm [11:0] $end
$var wire 32 ? dataW [31:0] $end
$var wire 32 @ dataMem_out [31:0] $end
$var wire 32 A data2 [31:0] $end
$var wire 32 B data1 [31:0] $end
$var wire 1 C bSel $end
$var wire 32 D alu_out [31:0] $end
$var wire 2 E aluSel [1:0] $end
$var wire 1 F WBSel $end
$var wire 5 G Rs2 [4:0] $end
$var wire 5 H Rs1 [4:0] $end
$var wire 5 I Rd [4:0] $end
$var wire 1 J MEMRW $end
$var wire 7 K Funct7 [6:0] $end
$var wire 3 L Funct3 [2:0] $end
$scope module a0 $end
$var wire 32 M b [31:0] $end
$var wire 32 N sum [31:0] $end
$var wire 32 O a [31:0] $end
$upscope $end
$scope module al0 $end
$var wire 32 P data2 [31:0] $end
$var wire 32 Q data1 [31:0] $end
$var wire 2 R ALUSel [1:0] $end
$var reg 32 S result [31:0] $end
$upscope $end
$scope module c0 $end
$var wire 7 T opcode [6:0] $end
$var wire 32 U instruction [31:0] $end
$var wire 7 V funct7 [6:0] $end
$var wire 3 W funct3 [2:0] $end
$var reg 2 X ALUSel [1:0] $end
$var reg 1 C BSel $end
$var reg 1 J MEMRW $end
$var reg 1 7 RegWrite $end
$var reg 1 F WBSel $end
$upscope $end
$scope module d0 $end
$var wire 7 Y opcode [6:0] $end
$var wire 32 Z instruction [31:0] $end
$var wire 7 [ OPCODE [6:0] $end
$var parameter 7 \ arithmetic_i1 $end
$var parameter 7 ] arithmetic_i2 $end
$var parameter 7 ^ arithmetic_r $end
$var reg 3 _ funct3 [2:0] $end
$var reg 7 ` funct7 [6:0] $end
$var reg 12 a immediate [11:0] $end
$var reg 5 b rd [4:0] $end
$var reg 5 c rs1 [4:0] $end
$var reg 5 d rs2 [4:0] $end
$upscope $end
$scope module dm0 $end
$var wire 1 J MEMRW $end
$var wire 32 e addr [31:0] $end
$var reg 32 f dataR [31:0] $end
$upscope $end
$scope module i0 $end
$var wire 1 , rst $end
$var wire 32 g instruction [31:0] $end
$var wire 32 h address [31:0] $end
$upscope $end
$scope module im0 $end
$var wire 32 i instruction [31:0] $end
$var wire 7 j opcode [6:0] $end
$var wire 12 k immediate_i [11:0] $end
$var parameter 7 l i_opcode1 $end
$var parameter 7 m i_opcode2 $end
$var reg 32 n immediate [31:0] $end
$upscope $end
$scope module m0 $end
$var wire 32 o a [31:0] $end
$var wire 1 C s $end
$var wire 32 p y [31:0] $end
$var wire 32 q b [31:0] $end
$upscope $end
$scope module m1 $end
$var wire 32 r a [31:0] $end
$var wire 32 s b [31:0] $end
$var wire 1 F s $end
$var wire 32 t y [31:0] $end
$upscope $end
$scope module p0 $end
$var wire 1 + clk $end
$var wire 32 u pc_in [31:0] $end
$var wire 1 , rst $end
$var reg 32 v pc_out [31:0] $end
$upscope $end
$scope module r0 $end
$var wire 32 w ReadData1 [31:0] $end
$var wire 32 x ReadData2 [31:0] $end
$var wire 1 7 RegWrite $end
$var wire 32 y WriteData [31:0] $end
$var wire 1 + clk $end
$var wire 5 z rd [4:0] $end
$var wire 5 { rs1 [4:0] $end
$var wire 5 | rs2 [4:0] $end
$upscope $end
$upscope $end
$upscope $end
$enddefinitions $end
$comment Show the parameter values. $end
$dumpall
b11 m
b10011 l
b110011 ^
b11 ]
b10011 \
$end
#0
$dumpvars
b1 |
b10 {
b11 z
b1011 y
b101 x
b110 w
b0 v
b100 u
b1011 t
bx s
b1011 r
b101 q
b101 p
bx o
bx n
b1 k
b110011 j
b100010000000110110011 i
b0 h
b100010000000110110011 g
bx f
b1011 e
b1 d
b10 c
b11 b
bx a
b0 `
b0 _
b110011 [
b100010000000110110011 Z
b110011 Y
b0 X
b0 W
b0 V
b100010000000110110011 U
b110011 T
b1011 S
b0 R
b110 Q
b101 P
b0 O
b100 N
b100 M
b0 L
b0 K
xJ
b11 I
b10 H
b1 G
1F
b0 E
b1011 D
0C
b110 B
b101 A
bx @
b1011 ?
bx >
bx =
b100010000000110110011 <
b101 ;
b110011 :
b100 9
b0 8
17
b1 6
b10 5
b100 4
b100010000000110110011 3
bx 2
b1011 1
bx 0
b101 /
b110 .
b1011 -
1,
1+
b1011 *
b110 )
b101 (
bx '
b1011 &
bx %
b100010000000110110011 $
b100 #
b10 "
b1 !
$end
#20000
0,
0+
#40000
b11111111111111111111100000111001 &
b11111111111111111111100000111001 1
b11111111111111111111100000111001 ?
b11111111111111111111100000111001 t
b11111111111111111111100000111001 y
b100000110100 >
b100000110100 a
b11111111111111111111100000110100 %
b11111111111111111111100000110100 2
b11111111111111111111100000110100 =
b11111111111111111111100000110100 n
b11111111111111111111100000110100 o
1C
b11111111111111111111100000110100 ;
b11111111111111111111100000110100 P
b11111111111111111111100000110100 p
b11111111111111111111100000111001 *
b11111111111111111111100000111001 -
b11111111111111111111100000111001 D
b11111111111111111111100000111001 S
b11111111111111111111100000111001 e
b11111111111111111111100000111001 r
b10011 j
b10011 :
b10011 [
b10011 Y
b10011 T
b100000110100 k
b1000001 V
bx K
bx `
bx (
bx /
bx A
bx q
bx x
bx !
bx 6
bx G
bx d
bx |
b101 )
b101 .
b101 B
b101 Q
b101 w
b1 "
b1 5
b1 H
b1 c
b1 {
b100 I
b100 b
b100 z
b10000011010000001000001000010011 $
b10000011010000001000001000010011 3
b10000011010000001000001000010011 <
b10000011010000001000001000010011 U
b10000011010000001000001000010011 Z
b10000011010000001000001000010011 g
b10000011010000001000001000010011 i
b1000 #
b1000 4
b1000 9
b1000 N
b1000 u
b100 8
b100 O
b100 h
b100 v
1+
#60000
0+
#80000
bx &
bx 1
bx ?
bx t
bx y
0J
0F
b1111101110 *
b1111101110 -
b1111101110 D
b1111101110 S
b1111101110 e
b1111101110 r
b1111101000 ;
b1111101000 P
b1111101000 p
b11 j
b11 :
b11 [
b11 Y
b11 T
b10 W
b1111101000 k
b11111 V
b1111101000 >
b1111101000 a
b110 )
b110 .
b110 B
b110 Q
b110 w
b10 "
b10 5
b10 H
b10 c
b10 {
b10 L
b10 _
b1010 I
b1010 b
b1010 z
b1111101000 %
b1111101000 2
b1111101000 =
b1111101000 n
b1111101000 o
b111110100000010010010100000011 $
b111110100000010010010100000011 3
b111110100000010010010100000011 <
b111110100000010010010100000011 U
b111110100000010010010100000011 Z
b111110100000010010010100000011 g
b111110100000010010010100000011 i
b1100 #
b1100 4
b1100 9
b1100 N
b1100 u
b1000 8
b1000 O
b1000 h
b1000 v
1+
#100000
0+
#120000
b0 K
b0 `
b0 (
b0 /
b0 A
b0 q
b0 x
b0 !
b0 6
b0 G
b0 d
b0 |
0C
07
b0 *
b0 -
b0 D
b0 S
b0 e
b0 r
b0 ;
b0 P
b0 p
bx j
bx :
bx [
bx Y
bx T
bx W
bx k
bx V
b0 >
b0 a
b0 )
b0 .
b0 B
b0 Q
b0 w
b0 "
b0 5
b0 H
b0 c
b0 {
b0 L
b0 _
b0 I
b0 b
b0 z
bx %
bx 2
bx =
bx n
bx o
bx $
bx 3
bx <
bx U
bx Z
bx g
bx i
b10000 #
b10000 4
b10000 9
b10000 N
b10000 u
b1100 8
b1100 O
b1100 h
b1100 v
1+
#140000
0+
#160000
b10100 #
b10100 4
b10100 9
b10100 N
b10100 u
b10000 8
b10000 O
b10000 h
b10000 v
1+
#180000
0+
#200000
b11000 #
b11000 4
b11000 9
b11000 N
b11000 u
b10100 8
b10100 O
b10100 h
b10100 v
1+
#220000
0+
#240000
b11100 #
b11100 4
b11100 9
b11100 N
b11100 u
b11000 8
b11000 O
b11000 h
b11000 v
1+
#260000
0+
#280000
b100000 #
b100000 4
b100000 9
b100000 N
b100000 u
b11100 8
b11100 O
b11100 h
b11100 v
1+
#300000
0+
#320000
b100100 #
b100100 4
b100100 9
b100100 N
b100100 u
b100000 8
b100000 O
b100000 h
b100000 v
1+
#340000
0+
#360000
b101000 #
b101000 4
b101000 9
b101000 N
b101000 u
b100100 8
b100100 O
b100100 h
b100100 v
1+
#380000
0+
#400000
b101100 #
b101100 4
b101100 9
b101100 N
b101100 u
b101000 8
b101000 O
b101000 h
b101000 v
1+
#420000
0+
#440000
b110000 #
b110000 4
b110000 9
b110000 N
b110000 u
b101100 8
b101100 O
b101100 h
b101100 v
1+
#460000
0+
#480000
b110100 #
b110100 4
b110100 9
b110100 N
b110100 u
b110000 8
b110000 O
b110000 h
b110000 v
1+
#500000
0+
#520000
b111000 #
b111000 4
b111000 9
b111000 N
b111000 u
b110100 8
b110100 O
b110100 h
b110100 v
1+
#540000
0+
#560000
b111100 #
b111100 4
b111100 9
b111100 N
b111100 u
b111000 8
b111000 O
b111000 h
b111000 v
1+
#580000
0+
#600000
b1000000 #
b1000000 4
b1000000 9
b1000000 N
b1000000 u
b111100 8
b111100 O
b111100 h
b111100 v
1+
#620000
0+
#640000
b1000100 #
b1000100 4
b1000100 9
b1000100 N
b1000100 u
b1000000 8
b1000000 O
b1000000 h
b1000000 v
1+
#660000
0+
#680000
b1001000 #
b1001000 4
b1001000 9
b1001000 N
b1001000 u
b1000100 8
b1000100 O
b1000100 h
b1000100 v
1+
#700000
0+
#720000
b1001100 #
b1001100 4
b1001100 9
b1001100 N
b1001100 u
b1001000 8
b1001000 O
b1001000 h
b1001000 v
1+
#740000
0+
#760000
b1010000 #
b1010000 4
b1010000 9
b1010000 N
b1010000 u
b1001100 8
b1001100 O
b1001100 h
b1001100 v
1+
#780000
0+
#800000
b1010100 #
b1010100 4
b1010100 9
b1010100 N
b1010100 u
b1010000 8
b1010000 O
b1010000 h
b1010000 v
1+
#820000
0+
#840000
b1011000 #
b1011000 4
b1011000 9
b1011000 N
b1011000 u
b1010100 8
b1010100 O
b1010100 h
b1010100 v
1+
#860000
0+
#880000
b1011100 #
b1011100 4
b1011100 9
b1011100 N
b1011100 u
b1011000 8
b1011000 O
b1011000 h
b1011000 v
1+
#900000
0+
#920000
b1100000 #
b1100000 4
b1100000 9
b1100000 N
b1100000 u
b1011100 8
b1011100 O
b1011100 h
b1011100 v
1+
#940000
0+
#960000
b1100100 #
b1100100 4
b1100100 9
b1100100 N
b1100100 u
b1100000 8
b1100000 O
b1100000 h
b1100000 v
1+
#980000
0+
#1000000
b1101000 #
b1101000 4
b1101000 9
b1101000 N
b1101000 u
b1100100 8
b1100100 O
b1100100 h
b1100100 v
1+
